LICENSE
MANIFEST.in
README.md
setup.py
LSparser/__init__.py
LSparser/__version__.py
LSparser.egg-info/PKG-INFO
LSparser.egg-info/SOURCES.txt
LSparser.egg-info/dependency_links.txt
LSparser.egg-info/top_level.txt
LSparser/command/__init__.py
LSparser/command/command.py
LSparser/command/core.py
LSparser/command/helper.py
LSparser/command/parser.py
LSparser/event/__init__.py
LSparser/event/command_event.py
LSparser/event/event.py
LSparser/event/event_manager.py
LSparser/util/__init__.py
LSparser/util/asyncs.py
LSparser/util/str.py
LSparser/util/str_similarity.py
test/test_async.py
test/test_cmd.py
test/test_core.py