Metadata-Version: 2.1
Name: LSparser
Version: 0.1.5
Summary: A command parser which breaks down a "command" into name, params, short & long options
Home-page: https://github.com/liggest/LSparser
Author: liggest
Author-email: liggest@sina.cn
License: MIT
Platform: UNKNOWN
Classifier: License :: OSI Approved :: MIT License
Classifier: Programming Language :: Python
Classifier: Programming Language :: Python :: 3
Classifier: Programming Language :: Python :: 3.6
Classifier: Programming Language :: Python :: 3.7
Classifier: Programming Language :: Python :: 3.8
Classifier: Programming Language :: Python :: Implementation :: CPython
Classifier: Programming Language :: Python :: Implementation :: PyPy
Requires-Python: >=3.6.0
